{"version":"0.4","title":"HerbFact_Contact","type":"page","content":[{"id":"18f959ab","settings":{"background_background":"classic","background_image":{"url":"http:\/\/6zt.4c5.myftpupload.com\/wp-content\/uploads\/2021\/01\/carlos-lindner-HW0jnv0ei08-unsplash-scaled.jpg","id":114},"background_size":"cover","layout":"full_width"},"elements":[{"id":"5150f13e","settings":{"_column_size":100,"_inline_size":null},"elements":[{"id":"62d8d608","settings":{"title":"Leave Us A Note!","align":"center","title_color":"#FEFEFF","typography_typography":"custom","typography_font_family":"Poppins","typography_font_size":{"unit":"px","size":43,"sizes":[]},"typography_font_weight":"600","_margin":{"unit":"px","top":"0","right":"0","bottom":"0","left":"0","isLinked":false},"_padding":{"unit":"px","top":"0200","right":"0","bottom":"200","left":"0","isLinked":false}},"elements":[],"isInner":false,"widgetType":"heading","elType":"widget"}],"isInner":false,"elType":"column"}],"isInner":false,"elType":"section"},{"id":"3d954048","settings":{"structure":"20","padding":{"unit":"px","top":"100","right":"0","bottom":"0","left":"0","isLinked":false}},"elements":[{"id":"60233588","settings":{"_column_size":50,"_inline_size":null},"elements":[{"id":"16a65a24","settings":{"title":"Contact info","title_color":"#000000","typography_typography":"custom","typography_font_family":"Poppins","typography_font_size":{"unit":"px","size":37,"sizes":[]},"typography_font_weight":"600","align":"center"},"elements":[],"isInner":false,"widgetType":"heading","elType":"widget"},{"id":"7fe5eaf1","settings":{"title":"Govind Puri ","align":"center","title_color":"#000000","typography_typography":"custom","typography_font_family":"Montserrat","typography_font_weight":"600"},"elements":[],"isInner":false,"widgetType":"heading","elType":"widget"},{"id":"5fb5192a","settings":{"title":"Okhla Phase III ","align":"center","title_color":"#000000","typography_typography":"custom","typography_font_family":"Montserrat","typography_font_weight":"600"},"elements":[],"isInner":false,"widgetType":"heading","elType":"widget"},{"id":"5be9e9cb","settings":{"title":"New Delhi -110020","align":"center","title_color":"#000000","typography_typography":"custom","typography_font_family":"Montserrat","typography_font_weight":"600"},"elements":[],"isInner":false,"widgetType":"heading","elType":"widget"},{"id":"6f208ab2","settings":{"title":"Email : HerbFacts2know@gmail.com","align":"center","title_color":"#000305","typography_typography":"custom","typography_font_family":"Montserrat","typography_font_size":{"unit":"px","size":19,"sizes":[]},"typography_font_weight":"500"},"elements":[],"isInner":false,"widgetType":"heading","elType":"widget"}],"isInner":false,"elType":"column"},{"id":"5c22fa16","settings":{"_column_size":50,"_inline_size":null},"elements":[{"id":"43b7aa13","settings":{"contact_form_list":"119","eael_contact_form_alignment":"center","eael_contact_form_max_width":{"unit":"px","size":389,"sizes":[]},"button_width_type":"full-width","_padding":{"unit":"px","top":"0","right":"0","bottom":"0","left":"0","isLinked":false}},"elements":[],"isInner":false,"widgetType":"eael-contact-form-7","elType":"widget"}],"isInner":false,"elType":"column"}],"isInner":false,"elType":"section"},{"id":"70215e10","settings":{"layout":"full_width","gap":"no"},"elements":[{"id":"8324fc7","settings":{"_column_size":100,"_inline_size":null},"elements":[{"id":"4d2d7bd5","settings":{"address":"delhi,india","height":{"unit":"px","size":500,"sizes":[]}},"elements":[],"isInner":false,"widgetType":"google_maps","elType":"widget"}],"isInner":false,"elType":"column"}],"isInner":false,"elType":"section"}],"page_settings":{"eael_ext_toc_title":"Table of Contents"}}